cogs/__init__.py
cogs/help.py
cogs/misc.py
cogs/verification_listener.py
src/__init__.py
src/bot.py
src/environment.py
src/log_setup.py
src/main.py
src/cogs/__init__.py
src/cogs/help.py
src/cogs/misc.py
src/cogs/verification_listener.py
discord_verification_listener-1.0.1.dist-info/METADATA
discord_verification_listener-1.0.1.dist-info/WHEEL
discord_verification_listener-1.0.1.dist-info/entry_points.txt
discord_verification_listener-1.0.1.dist-info/top_level.txt
discord_verification_listener-1.0.1.dist-info/RECORD
