Metadata-Version: 2.1
Name: discord-verification-listener
Version: 1.0.1
Summary: A simple verification bot for discord
Home-page: https://github.com/Info-Bonn/verification-listener
Author: nonchris
Author-email: info@nonchris.eu
License: UNKNOWN
Project-URL: Bug Reports, https://github.com/Info-Bonn/verification-listener/issues
Project-URL: Source, https://github.com/Info-Bonn/verification-listener
Keywords: discord-bot,verification
Platform: UNKNOWN
Classifier: Development Status :: 5 - Production/Stable
Classifier: Environment :: Console
Classifier: Intended Audience :: Other Audience
Classifier: Topic :: Communications :: Chat
Classifier: Typing :: Typed
Classifier: License :: OSI Approved :: GNU General Public License v3 (GPLv3)
Classifier: Programming Language :: Python :: 3
Classifier: Programming Language :: Python :: 3.8
Classifier: Programming Language :: Python :: 3.9
Classifier: Programming Language :: Python :: 3 :: Only
Requires-Python: >=3.8, <4
Requires-Dist: discord.py (~=1.7.2)
